arazzo_runner-0.9.2.dist-info/METADATA
arazzo_runner-0.9.2.dist-info/WHEEL
arazzo_runner-0.9.2.dist-info/entry_points.txt
arazzo_runner-0.9.2.dist-info/licenses/LICENSE
arazzo_runner-0.9.2.dist-info/licenses/NOTICE
arazzo_runner/__init__.py
arazzo_runner/__main__.py
arazzo_runner/auth/__init__.py
arazzo_runner/auth/auth_parser.py
arazzo_runner/auth/auth_processor.py
arazzo_runner/auth/credentials/__init__.py
arazzo_runner/auth/credentials/fetch.py
arazzo_runner/auth/credentials/models.py
arazzo_runner/auth/credentials/provider.py
arazzo_runner/auth/credentials/transform.py
arazzo_runner/auth/credentials/validate.py
arazzo_runner/auth/models.py
arazzo_runner/blob_store.py
arazzo_runner/blob_utils.py
arazzo_runner/evaluator.py
arazzo_runner/executor.py
arazzo_runner/executor/__init__.py
arazzo_runner/executor/action_handler.py
arazzo_runner/executor/operation_finder.py
arazzo_runner/executor/output_extractor.py
arazzo_runner/executor/parameter_processor.py
arazzo_runner/executor/server_processor.py
arazzo_runner/executor/step_executor.py
arazzo_runner/executor/success_criteria.py
arazzo_runner/extractor/openapi_extractor.py
arazzo_runner/http.py
arazzo_runner/models.py
arazzo_runner/runner.py
arazzo_runner/utils.py
arazzo_runner-0.9.2.dist-info/RECORD
