Metadata-Version: 2.4
Name: arazzo_runner
Version: 0.9.2
Summary: Execution libraries and test tools for Arazzo workflows and Open API operations
Author-Email: Jentic <hello@jentic.com>
License-Expression: Apache-2.0
License-File: LICENSE
License-File: NOTICE
Project-URL: Homepage, https://github.com/jentic/arazzo-engine
Project-URL: Documentation, https://github.com/jentic/arazzo-engine#readme
Project-URL: Issues, https://github.com/jentic/arazzo-engine/issues
Requires-Python: <4.0,>=3.11
Requires-Dist: pydantic>=2.0.0
Requires-Dist: pyyaml>=6.0
Requires-Dist: requests>=2.28.0
Requires-Dist: jsonpath-ng>=1.5.0
Requires-Dist: jsonpointer>=3.0.0
